oooo/__init__.py
oooo/__version__.py
oooo-0.1.0.dist-info/LICENSE
oooo-0.1.0.dist-info/METADATA
oooo-0.1.0.dist-info/WHEEL
oooo-0.1.0.dist-info/top_level.txt
oooo-0.1.0.dist-info/RECORD
